easy_start_qunjielong/__init__.py
easy_start_qunjielong/open.py
easy_start_qunjielong-0.1.1.dist-info/licenses/LICENSE
easy_start_qunjielong-0.1.1.dist-info/METADATA
easy_start_qunjielong-0.1.1.dist-info/WHEEL
easy_start_qunjielong-0.1.1.dist-info/top_level.txt
easy_start_qunjielong-0.1.1.dist-info/RECORD
